{
  "2025-06-16": {
    "hint": "A equals D",
    "fromLetter": "A",
    "toLetter": "D",
    "puzzleLines": [
      "MQFFXL’M FIIBGBDO PJMBKQDSBFQ",
      "OJSSJP UDM OJDWJA FRS BQSF STJ",
      "XRNOBG. BS MBHXOL MSDSJA: “B’H",
      "SBPJA FI UFPWBQK IFP",
      "XJDQRSM.”"
    ],
    "solutionLines": [
      "SNOOPY’S OFFICIAL RESIGNATION",
      "LETTER WAS LEAKED OUT INTO THE",
      "PUBLIC. IT SIMPLY STATED: “I’M",
      "TIRED OF WORKING FOR",
      "PEANUTS.”"
    ]
  },
  "2025-06-17": {
    "hint": "D equals N",
    "fromLetter": "D",
    "toLetter": "N",
    "puzzleLines": [
      "LDXXMF’L XHHSPSCI OKLSQDCVSXD",
      "IKVVKO BCL IKCTKY XZV SDVX VWK",
      "MZEISP. SV LSAMIF LVCVKY: “S’A",
      "VSOKY XH BXOTSDQ HXO",
      "MKCDZVL.”"
    ],
    "solutionLines": [
      "SNOOPY’S OFFICIAL RESIGNATION",
      "LETTER WAS LEAKED OUT INTO THE",
      "PUBLIC. IT SIMPLY STATED: “I’M",
      "TIRED OF WORKING FOR",
      "PEANUTS.”"
    ]
  },
  "2025-06-18": {
    "hint": "J equals Y",
    "fromLetter": "J",
    "toLetter": "Y",
    "puzzleLines": [
      "HREEAJ’H ETTZUZPQ GKHZXRPDZER",
      "QKDDKG FPH QKPYKS EWD ZRDE DNK",
      "AWCQZU. ZD HZIAQJ HDPDKS: “Z’I",
      "DZGKS ET FEGYZRX TEG",
      "AKPRWDH.”"
    ],
    "solutionLines": [
      "SNOOPY’S OFFICIAL RESIGNATION",
      "LETTER WAS LEAKED OUT INTO THE",
      "PUBLIC. IT SIMPLY STATED: “I’M",
      "TIRED OF WORKING FOR",
      "PEANUTS.”"
    ]
  },
  "2025-06-19": {
    "hint": "L equals M",
    "fromLetter": "L",
    "toLetter": "M",
    "puzzleLines": [
      "EYDDVU’E DZZTJTWI MOETKYWCTDY",
      "IOCCOM NWE IOWSOQ DRC TYCD CAO",
      "VRHITJ. TC ETLVIU ECWCOQ: “T’L",
      "CTMOQ DZ NDMSTYK ZDM",
      "VOWYRCE.”"
    ],
    "solutionLines": [
      "SNOOPY’S OFFICIAL RESIGNATION",
      "LETTER WAS LEAKED OUT INTO THE",
      "PUBLIC. IT SIMPLY STATED: “I’M",
      "TIRED OF WORKING FOR",
      "PEANUTS.”"
    ]
  },
  "2025-06-20": {
    "hint": "Q equals R",
    "fromLetter": "Q",
    "toLetter": "R",
    "puzzleLines": [
      "GYHHCO’G HNNJPJLU QBGJEYLWJHY",
      "UBWWBQ SLG UBLFBA HXW JYWH WDB",
      "CXTUJP. JW GJZCUO GWLWBA: “J’Z",
      "WJQBA HN SHQFJYE NHQ CBLYXWG.”"
    ],
    "solutionLines": [
      "SNOOPY’S OFFICIAL RESIGNATION",
      "LETTER WAS LEAKED OUT INTO THE",
      "PUBLIC. IT SIMPLY STATED: “I’M",
      "TIRED OF WORKING FOR PEANUTS.”"
    ]
  }
}